{
  "datas": [
    {
      "id": "u1",
      "name": "Cbb0fe",
      "img": "https://pbs.twimg.com/profile_images/1749792005251620864/Af6z5kSC_400x400.jpg",
      "owned_rooms": "10",
      "joined_rooms": 0
    },
    {
      "id": "u2",
      "name": "Nuoanunu",
      "img": "https://pics.craiyon.com/2024-09-07/8MQVM4YgTxanrjwKBrMLwg.webp",
      "owned_rooms": "3",
      "joined_rooms": 0
    },
    {
      "id": "u3",
      "name": "Clemente",
      "img": "https://pbs.twimg.com/profile_images/1676401842815901696/rO62w0Cr_400x400.jpg",
      "owned_rooms": "1",
      "joined_rooms": 0
    },
    {
      "id": "u4",
      "name": "thiccy",
      "img": "https://pbs.twimg.com/profile_images/1710677165375737856/-q8mANoN_400x400.jpg",
      "owned_rooms": "1",
      "joined_rooms": 1
    },
    {
      "id": "u5",
      "name": "gainzy",
      "img": "https://pbs.twimg.com/profile_images/1763753850240983040/bg9hu_kW_400x400.jpg",
      "owned_rooms": "1",
      "joined_rooms": 1
    },
    {
      "id": "u6",
      "name": "mochi",
      "img": "https://pbs.twimg.com/profile_images/1676246952131043330/a_9p7KnH_400x400.jpg",
      "owned_rooms": "0",
      "joined_rooms": 2
    },
    {
      "id": "u7",
      "name": "Charlotte Fang",
      "img": "https://pbs.twimg.com/profile_images/1827602713426657281/oW6MAiLZ_400x400.jpg",
      "owned_rooms": "0",
      "joined_rooms": 2
    },
    {
      "id": "u8",
      "name": "Aura",
      "img": "https://pbs.twimg.com/profile_images/1674133547261612039/A6rA26IH_400x400.jpg",
      "owned_rooms": "0",
      "joined_rooms": 4
    },
    {
      "id": "u9",
      "name": "Impossible Finance",
      "img": "https://pbs.twimg.com/profile_images/1388056927167340544/9SxWPsH6_400x400.jpg",
      "owned_rooms": "0",
      "joined_rooms": 4
    },
    {
      "id": "u9",
      "name": "smolting",
      "img": "https://pbs.twimg.com/profile_images/1812298915661623296/P0Yj0Xgq_400x400.jpg",
      "owned_rooms": "0",
      "joined_rooms": 4
    },
    {
      "id": "u10",
      "name": "cnig69",
      "img": "https://pbs.twimg.com/profile_images/1801484195572944896/j3DV-55y_400x400.jpg",
      "owned_rooms": "0",
      "joined_rooms": 4
    },
    {
      "id": "u11",
      "name": "tre",
      "img": "https://pbs.twimg.com/profile_images/1812315870531653632/FLCbRjFo_400x400.jpg",
      "owned_rooms": "0",
      "joined_rooms": 4
    },
    {
      "id": "u12",
      "name": "theo2k2",
      "img": "https://pbs.twimg.com/profile_images/1790213542643113984/YUXdLchG_400x400.jpg",
      "owned_rooms": "0",
      "joined_rooms": 4
    },
    {
      "id": "u13",
      "name": "RonnieDcky",
      "img": "https://pbs.twimg.com/profile_images/1704981181702283264/GlWbCXMJ_400x400.jpg",
      "owned_rooms": "0",
      "joined_rooms": 4
    },
    {
      "id": "u14",
      "name": "JpegXBT",
      "img": "https://pbs.twimg.com/profile_images/1838353395893309441/Lakv97Ke_400x400.jpg",
      "owned_rooms": "0",
      "joined_rooms": 4
    },
    {
      "id": "u15",
      "name": "RookieXBT",
      "img": "https://pbs.twimg.com/profile_images/1613188823411838976/LzWlW37g_400x400.jpg",
      "owned_rooms": "0",
      "joined_rooms": 4
    },
    {
      "id": "u16",
      "name": "trader1sz",
      "img": "https://pbs.twimg.com/profile_images/1829911783164788736/_lW5FWLz_400x400.jpg",
      "owned_rooms": "0",
      "joined_rooms": 4
    },
    {
      "id": "u17",
      "name": "Hyung Prada",
      "img": "https://pbs.twimg.com/profile_images/1837674325857484801/rniUEBZ0_400x400.jpg",
      "owned_rooms": "0",
      "joined_rooms": 4
    },
    {
      "id": "u18",
      "name": "DonAlt",
      "img": "https://pbs.twimg.com/profile_images/1805463878471417857/hXKyF93b_400x400.png",
      "owned_rooms": "0",
      "joined_rooms": 4
    },
    {
      "id": "u19",
      "name": "kush",
      "img": "https://pbs.twimg.com/profile_images/1778333305135595520/0rYRolb8_400x400.jpg",
      "owned_rooms": "0",
      "joined_rooms": 4
    },
    {
      "id": "u20",
      "name": "jercky",
      "img": "https://pbs.twimg.com/profile_images/1826221965167783936/BRYla5Q7_400x400.jpg",
      "owned_rooms": "0",
      "joined_rooms": 4
    },
    {
      "id": "u21",
      "name": "blackswanlake",
      "img": "https://pbs.twimg.com/profile_images/1790571528544985088/DR7xJHzt_400x400.jpg",
      "owned_rooms": "0",
      "joined_rooms": 4
    },
    {
      "id": "u22",
      "name": "kongee",
      "img": "https://pbs.twimg.com/profile_images/1777121375079022592/KjBqi4ZG_400x400.jpg",
      "owned_rooms": "0",
      "joined_rooms": 4
    },
    {
      "id": "u23",
      "name": "Servant of the Cabal",
      "img": "https://i.ibb.co/4d6Mqb6/2024-09-25-12-57-34.jpg”",
      "owned_rooms": "0",
      "joined_rooms": 4,
      "bot": true
    }
  ]
}
